connectiva/__init__.py
connectiva-0.1.0.dist-info/LICENSE
connectiva-0.1.0.dist-info/METADATA
connectiva-0.1.0.dist-info/WHEEL
connectiva-0.1.0.dist-info/RECORD
