Metadata-Version: 2.1
Name: connectiva
Version: 0.1.0
Summary: A Unified Microservice Communication Library
License: MIT
Keywords: microservices,communication,REST,gRPC,Kafka,WebSockets,GraphQL
Author: Ali Tavallaie
Author-email: a.tavallaie@gmail.com
Requires-Python: >=3.10,<4.0
Classifier: License :: OSI Approved :: MIT License
Classifier: Programming Language :: Python :: 3
Classifier: Programming Language :: Python :: 3.10
Classifier: Programming Language :: Python :: 3.11
Classifier: Programming Language :: Python :: 3.12
